vtstudio/__init__.py
vtstudio/__main__.py
vtstudio/client.py
vtubebridge-0.2.2.dist-info/METADATA
vtubebridge-0.2.2.dist-info/WHEEL
vtubebridge-0.2.2.dist-info/top_level.txt
vtubebridge-0.2.2.dist-info/RECORD
