Metadata-Version: 2.4
Name: VTubeBridge
Version: 0.2.2
Summary: A fully featured Python wrapper for the VTube Studio API
Home-page: https://v0-tesst-bf8bpxqdsin.vercel.app/
Author: Araxyso
Author-email: zinedinarnaut085@gmail.com
Project-URL: Homepage, https://v0-tesst-bf8bpxqdsin.vercel.app/
Project-URL: Source, https://github.com/Zinedinarnaut/VTubeBridge
Project-URL: Bug Tracker, https://github.com/Zinedinarnaut/VTubeBridge/issues
Classifier: Development Status :: 4 - Beta
Classifier: Intended Audience :: Developers
Classifier: License :: OSI Approved :: MIT License
Classifier: Programming Language :: Python :: 3
Classifier: Programming Language :: Python :: 3.11
Classifier: Operating System :: OS Independent
Classifier: Topic :: Software Development :: Libraries
Classifier: Topic :: Multimedia :: Graphics
Requires-Python: >=3.11
Requires-Dist: websockets
Dynamic: author
Dynamic: author-email
Dynamic: classifier
Dynamic: description
Dynamic: description-content-type
Dynamic: home-page
Dynamic: project-url
Dynamic: requires-dist
Dynamic: requires-python
Dynamic: summary
